odoo/addons/fieldservice_partner_fax/README.rst
odoo/addons/fieldservice_partner_fax/__init__.py
odoo/addons/fieldservice_partner_fax/__manifest__.py
odoo/addons/fieldservice_partner_fax/i18n/fieldservice_partner_fax.pot
odoo/addons/fieldservice_partner_fax/readme/CONTRIBUTORS.rst
odoo/addons/fieldservice_partner_fax/readme/DESCRIPTION.rst
odoo/addons/fieldservice_partner_fax/readme/USAGE.rst
odoo/addons/fieldservice_partner_fax/static/description/icon.png
odoo/addons/fieldservice_partner_fax/static/description/index.html
odoo/addons/fieldservice_partner_fax/views/fsm_location.xml
odoo13_addon_fieldservice_partner_fax-13.0.1.1.0.dist-info/METADATA
odoo13_addon_fieldservice_partner_fax-13.0.1.1.0.dist-info/WHEEL
odoo13_addon_fieldservice_partner_fax-13.0.1.1.0.dist-info/top_level.txt
odoo13_addon_fieldservice_partner_fax-13.0.1.1.0.dist-info/RECORD
