Metadata-Version: 2.1
Name: odoo13-addon-fieldservice-partner-fax
Version: 13.0.1.1.0
Summary: This module allows you to manage a partner's fax number from the field service location screen.
Home-page: https://github.com/OCA/field-service
Author: Open Source Integrators, Odoo Community Association (OCA)
Author-email: support@odoo-community.org
License: AGPL-3
Platform: UNKNOWN
Classifier: Programming Language :: Python
Classifier: Framework :: Odoo
Classifier: License :: OSI Approved :: GNU Affero General Public License v3
Classifier: Development Status :: 4 - Beta
Requires-Python: >=3.5
Requires-Dist: odoo13-addon-fieldservice
Requires-Dist: odoo13-addon-partner-fax
Requires-Dist: odoo (<13.1dev,>=13.0a)
